[
  {
    "matrix": 100,
    "block": 16,
    "cache": "16kB",
    "assoc": 4,
    "type": "ns",
    "value": 3.903074
  },
  {
    "matrix": 100,
    "block": 16,
    "cache": "16kB",
    "assoc": 8,
    "type": "ns",
    "value": 3.904584
  },
  {
    "matrix": 100,
    "block": 16,
    "cache": "32kB",
    "assoc": 4,
    "type": "ns",
    "value": 3.88347
  },
  {
    "matrix": 100,
    "block": 16,
    "cache": "32kB",
    "assoc": 8,
    "type": "ns",
    "value": 3.882883
  },
  {
    "matrix": 100,
    "block": 16,
    "cache": "64kB",
    "assoc": 4,
    "type": "ns",
    "value": 3.873567
  },
  {
    "matrix": 100,
    "block": 16,
    "cache": "64kB",
    "assoc": 8,
    "type": "ns",
    "value": 3.87449
  },
  {
    "matrix": 100,
    "block": 32,
    "cache": "16kB",
    "assoc": 4,
    "type": "ns",
    "value": 3.888701
  },
  {
    "matrix": 100,
    "block": 32,
    "cache": "16kB",
    "assoc": 8,
    "type": "ns",
    "value": 3.888784
  },
  {
    "matrix": 100,
    "block": 32,
    "cache": "32kB",
    "assoc": 4,
    "type": "ns",
    "value": 3.88635
  },
  {
    "matrix": 100,
    "block": 32,
    "cache": "32kB",
    "assoc": 8,
    "type": "ns",
    "value": 3.886815
  },
  {
    "matrix": 100,
    "block": 32,
    "cache": "64kB",
    "assoc": 4,
    "type": "ns",
    "value": 3.87917
  },
  {
    "matrix": 100,
    "block": 32,
    "cache": "64kB",
    "assoc": 8,
    "type": "ns",
    "value": 3.879374
  },
  {
    "matrix": 100,
    "block": 64,
    "cache": "16kB",
    "assoc": 4,
    "type": "ns",
    "value": 3.933748
  },
  {
    "matrix": 100,
    "block": 64,
    "cache": "16kB",
    "assoc": 8,
    "type": "ns",
    "value": 3.939729
  },
  {
    "matrix": 100,
    "block": 64,
    "cache": "32kB",
    "assoc": 4,
    "type": "ns",
    "value": 3.885098
  },
  {
    "matrix": 100,
    "block": 64,
    "cache": "32kB",
    "assoc": 8,
    "type": "ns",
    "value": 3.884276
  },
  {
    "matrix": 100,
    "block": 64,
    "cache": "64kB",
    "assoc": 4,
    "type": "ns",
    "value": 3.881959
  },
  {
    "matrix": 100,
    "block": 64,
    "cache": "64kB",
    "assoc": 8,
    "type": "ns",
    "value": 3.882288
  },
  {
    "matrix": 128,
    "block": 16,
    "cache": "16kB",
    "assoc": 4,
    "type": "ns",
    "value": 3.893881
  },
  {
    "matrix": 128,
    "block": 16,
    "cache": "16kB",
    "assoc": 8,
    "type": "ns",
    "value": 3.893892
  },
  {
    "matrix": 128,
    "block": 16,
    "cache": "32kB",
    "assoc": 4,
    "type": "ns",
    "value": 3.883303
  },
  {
    "matrix": 128,
    "block": 16,
    "cache": "32kB",
    "assoc": 8,
    "type": "ns",
    "value": 3.883206
  },
  {
    "matrix": 128,
    "block": 16,
    "cache": "64kB",
    "assoc": 4,
    "type": "ns",
    "value": 3.87771
  },
  {
    "matrix": 128,
    "block": 16,
    "cache": "64kB",
    "assoc": 8,
    "type": "ns",
    "value": 3.876757
  },
  {
    "matrix": 128,
    "block": 32,
    "cache": "16kB",
    "assoc": 4,
    "type": "ns",
    "value": 3.885081
  },
  {
    "matrix": 128,
    "block": 32,
    "cache": "16kB",
    "assoc": 8,
    "type": "ns",
    "value": 3.885087
  },
  {
    "matrix": 128,
    "block": 32,
    "cache": "32kB",
    "assoc": 4,
    "type": "ns",
    "value": 3.884638
  },
  {
    "matrix": 128,
    "block": 32,
    "cache": "32kB",
    "assoc": 8,
    "type": "ns",
    "value": 3.88512
  },
  {
    "matrix": 128,
    "block": 32,
    "cache": "64kB",
    "assoc": 4,
    "type": "ns",
    "value": 3.882062
  },
  {
    "matrix": 128,
    "block": 32,
    "cache": "64kB",
    "assoc": 8,
    "type": "ns",
    "value": 3.880047
  },
  {
    "matrix": 128,
    "block": 64,
    "cache": "16kB",
    "assoc": 4,
    "type": "ns",
    "value": 4.000878
  },
  {
    "matrix": 128,
    "block": 64,
    "cache": "16kB",
    "assoc": 8,
    "type": "ns",
    "value": 4.019976
  },
  {
    "matrix": 128,
    "block": 64,
    "cache": "32kB",
    "assoc": 4,
    "type": "ns",
    "value": 3.884656
  },
  {
    "matrix": 128,
    "block": 64,
    "cache": "32kB",
    "assoc": 8,
    "type": "ns",
    "value": 3.882632
  },
  {
    "matrix": 128,
    "block": 64,
    "cache": "64kB",
    "assoc": 4,
    "type": "ns",
    "value": 3.882248
  },
  {
    "matrix": 128,
    "block": 64,
    "cache": "64kB",
    "assoc": 8,
    "type": "ns",
    "value": 3.882499
  },
  {
    "matrix": 128,
    "block": 128,
    "cache": "16kB",
    "assoc": 4,
    "type": "ns",
    "value": 4.054546
  },
  {
    "matrix": 128,
    "block": 128,
    "cache": "16kB",
    "assoc": 8,
    "type": "ns",
    "value": 4.01389
  },
  {
    "matrix": 128,
    "block": 128,
    "cache": "32kB",
    "assoc": 4,
    "type": "ns",
    "value": 4.013923
  },
  {
    "matrix": 128,
    "block": 128,
    "cache": "32kB",
    "assoc": 8,
    "type": "ns",
    "value": 4.013858
  },
  {
    "matrix": 128,
    "block": 128,
    "cache": "64kB",
    "assoc": 4,
    "type": "ns",
    "value": 3.948969
  },
  {
    "matrix": 128,
    "block": 128,
    "cache": "64kB",
    "assoc": 8,
    "type": "ns",
    "value": 3.981354
  },
  {
    "matrix": 200,
    "block": 16,
    "cache": "16kB",
    "assoc": 4,
    "type": "ns",
    "value": 3.893981
  },
  {
    "matrix": 200,
    "block": 16,
    "cache": "16kB",
    "assoc": 8,
    "type": "ns",
    "value": 3.893579
  },
  {
    "matrix": 200,
    "block": 16,
    "cache": "32kB",
    "assoc": 4,
    "type": "ns",
    "value": 3.892336
  },
  {
    "matrix": 200,
    "block": 16,
    "cache": "32kB",
    "assoc": 8,
    "type": "ns",
    "value": 3.8926
  },
  {
    "matrix": 200,
    "block": 16,
    "cache": "64kB",
    "assoc": 4,
    "type": "ns",
    "value": 3.879116
  },
  {
    "matrix": 200,
    "block": 16,
    "cache": "64kB",
    "assoc": 8,
    "type": "ns",
    "value": 3.875352
  },
  {
    "matrix": 200,
    "block": 32,
    "cache": "16kB",
    "assoc": 4,
    "type": "ns",
    "value": 3.899982
  },
  {
    "matrix": 200,
    "block": 32,
    "cache": "16kB",
    "assoc": 8,
    "type": "ns",
    "value": 3.884606
  },
  {
    "matrix": 200,
    "block": 32,
    "cache": "32kB",
    "assoc": 4,
    "type": "ns",
    "value": 3.884527
  },
  {
    "matrix": 200,
    "block": 32,
    "cache": "32kB",
    "assoc": 8,
    "type": "ns",
    "value": 3.884546
  },
  {
    "matrix": 200,
    "block": 32,
    "cache": "64kB",
    "assoc": 4,
    "type": "ns",
    "value": 3.882114
  },
  {
    "matrix": 200,
    "block": 32,
    "cache": "64kB",
    "assoc": 8,
    "type": "ns",
    "value": 3.882396
  },
  {
    "matrix": 200,
    "block": 64,
    "cache": "16kB",
    "assoc": 4,
    "type": "ns",
    "value": 3.991819
  },
  {
    "matrix": 200,
    "block": 64,
    "cache": "16kB",
    "assoc": 8,
    "type": "ns",
    "value": 4.006583
  },
  {
    "matrix": 200,
    "block": 64,
    "cache": "32kB",
    "assoc": 4,
    "type": "ns",
    "value": 3.885809
  },
  {
    "matrix": 200,
    "block": 64,
    "cache": "32kB",
    "assoc": 8,
    "type": "ns",
    "value": 3.883474
  },
  {
    "matrix": 200,
    "block": 64,
    "cache": "64kB",
    "assoc": 4,
    "type": "ns",
    "value": 3.881632
  },
  {
    "matrix": 200,
    "block": 64,
    "cache": "64kB",
    "assoc": 8,
    "type": "ns",
    "value": 3.881639
  },
  {
    "matrix": 200,
    "block": 128,
    "cache": "16kB",
    "assoc": 4,
    "type": "ns",
    "value": 4.077851
  },
  {
    "matrix": 200,
    "block": 128,
    "cache": "16kB",
    "assoc": 8,
    "type": "ns",
    "value": 4.023904
  },
  {
    "matrix": 200,
    "block": 128,
    "cache": "32kB",
    "assoc": 4,
    "type": "ns",
    "value": 3.995602
  },
  {
    "matrix": 200,
    "block": 128,
    "cache": "32kB",
    "assoc": 8,
    "type": "ns",
    "value": 4.000779
  },
  {
    "matrix": 200,
    "block": 128,
    "cache": "64kB",
    "assoc": 4,
    "type": "ns",
    "value": 3.915476
  },
  {
    "matrix": 200,
    "block": 128,
    "cache": "64kB",
    "assoc": 8,
    "type": "ns",
    "value": 3.921942
  },
  {
    "matrix": 256,
    "block": 16,
    "cache": "16kB",
    "assoc": 4,
    "type": "ns",
    "value": 3.892319
  },
  {
    "matrix": 256,
    "block": 16,
    "cache": "16kB",
    "assoc": 8,
    "type": "ns",
    "value": 3.892218
  },
  {
    "matrix": 256,
    "block": 16,
    "cache": "32kB",
    "assoc": 4,
    "type": "ns",
    "value": 3.890628
  },
  {
    "matrix": 256,
    "block": 16,
    "cache": "32kB",
    "assoc": 8,
    "type": "ns",
    "value": 3.892285
  },
  {
    "matrix": 256,
    "block": 16,
    "cache": "64kB",
    "assoc": 4,
    "type": "ns",
    "value": 3.886996
  },
  {
    "matrix": 256,
    "block": 16,
    "cache": "64kB",
    "assoc": 8,
    "type": "ns",
    "value": 3.884228
  },
  {
    "matrix": 256,
    "block": 32,
    "cache": "16kB",
    "assoc": 4,
    "type": "ns",
    "value": 3.884513
  },
  {
    "matrix": 256,
    "block": 32,
    "cache": "16kB",
    "assoc": 8,
    "type": "ns",
    "value": 3.883275
  },
  {
    "matrix": 256,
    "block": 32,
    "cache": "32kB",
    "assoc": 4,
    "type": "ns",
    "value": 3.883227
  },
  {
    "matrix": 256,
    "block": 32,
    "cache": "32kB",
    "assoc": 8,
    "type": "ns",
    "value": 3.883274
  },
  {
    "matrix": 256,
    "block": 32,
    "cache": "64kB",
    "assoc": 4,
    "type": "ns",
    "value": 3.882281
  },
  {
    "matrix": 256,
    "block": 32,
    "cache": "64kB",
    "assoc": 8,
    "type": "ns",
    "value": 3.882485
  },
  {
    "matrix": 256,
    "block": 64,
    "cache": "16kB",
    "assoc": 4,
    "type": "ns",
    "value": 4.043688
  },
  {
    "matrix": 256,
    "block": 64,
    "cache": "16kB",
    "assoc": 8,
    "type": "ns",
    "value": 4.029943
  },
  {
    "matrix": 256,
    "block": 64,
    "cache": "32kB",
    "assoc": 4,
    "type": "ns",
    "value": 3.900879
  },
  {
    "matrix": 256,
    "block": 64,
    "cache": "32kB",
    "assoc": 8,
    "type": "ns",
    "value": 3.881631
  },
  {
    "matrix": 256,
    "block": 64,
    "cache": "64kB",
    "assoc": 4,
    "type": "ns",
    "value": 3.88454
  },
  {
    "matrix": 256,
    "block": 64,
    "cache": "64kB",
    "assoc": 8,
    "type": "ns",
    "value": 3.88085
  },
  {
    "matrix": 256,
    "block": 128,
    "cache": "16kB",
    "assoc": 4,
    "type": "ns",
    "value": 4.487338
  },
  {
    "matrix": 256,
    "block": 128,
    "cache": "16kB",
    "assoc": 8,
    "type": "ns",
    "value": 4.037055
  },
  {
    "matrix": 256,
    "block": 128,
    "cache": "32kB",
    "assoc": 4,
    "type": "ns",
    "value": 4.265113
  },
  {
    "matrix": 256,
    "block": 128,
    "cache": "32kB",
    "assoc": 8,
    "type": "ns",
    "value": 4.036198
  },
  {
    "matrix": 256,
    "block": 128,
    "cache": "64kB",
    "assoc": 4,
    "type": "ns",
    "value": 4.129038
  },
  {
    "matrix": 256,
    "block": 128,
    "cache": "64kB",
    "assoc": 8,
    "type": "ns",
    "value": 3.975636
  },
  {
    "matrix": 256,
    "block": 256,
    "cache": "16kB",
    "assoc": 4,
    "type": "ns",
    "value": 5.428764
  },
  {
    "matrix": 256,
    "block": 256,
    "cache": "16kB",
    "assoc": 8,
    "type": "ns",
    "value": 6.03789
  },
  {
    "matrix": 256,
    "block": 256,
    "cache": "32kB",
    "assoc": 4,
    "type": "ns",
    "value": 4.615559
  },
  {
    "matrix": 256,
    "block": 256,
    "cache": "32kB",
    "assoc": 8,
    "type": "ns",
    "value": 4.040189
  },
  {
    "matrix": 256,
    "block": 256,
    "cache": "64kB",
    "assoc": 4,
    "type": "ns",
    "value": 4.325284
  },
  {
    "matrix": 256,
    "block": 256,
    "cache": "64kB",
    "assoc": 8,
    "type": "ns",
    "value": 4.040154
  },
  {
    "matrix": 512,
    "block": 16,
    "cache": "16kB",
    "assoc": 4,
    "type": "ns",
    "value": 3.89202
  },
  {
    "matrix": 512,
    "block": 16,
    "cache": "16kB",
    "assoc": 8,
    "type": "ns",
    "value": 3.891431
  },
  {
    "matrix": 512,
    "block": 16,
    "cache": "32kB",
    "assoc": 4,
    "type": "ns",
    "value": 3.891426
  },
  {
    "matrix": 512,
    "block": 16,
    "cache": "32kB",
    "assoc": 8,
    "type": "ns",
    "value": 3.891428
  },
  {
    "matrix": 512,
    "block": 16,
    "cache": "64kB",
    "assoc": 4,
    "type": "ns",
    "value": 3.891414
  },
  {
    "matrix": 512,
    "block": 16,
    "cache": "64kB",
    "assoc": 8,
    "type": "ns",
    "value": 3.891401
  },
  {
    "matrix": 512,
    "block": 32,
    "cache": "16kB",
    "assoc": 4,
    "type": "ns",
    "value": 3.88336
  },
  {
    "matrix": 512,
    "block": 32,
    "cache": "16kB",
    "assoc": 8,
    "type": "ns",
    "value": 3.88261
  },
  {
    "matrix": 512,
    "block": 32,
    "cache": "32kB",
    "assoc": 4,
    "type": "ns",
    "value": 3.882559
  },
  {
    "matrix": 512,
    "block": 32,
    "cache": "32kB",
    "assoc": 8,
    "type": "ns",
    "value": 3.882547
  },
  {
    "matrix": 512,
    "block": 32,
    "cache": "64kB",
    "assoc": 4,
    "type": "ns",
    "value": 3.882547
  },
  {
    "matrix": 512,
    "block": 32,
    "cache": "64kB",
    "assoc": 8,
    "type": "ns",
    "value": 3.88255
  },
  {
    "matrix": 512,
    "block": 64,
    "cache": "16kB",
    "assoc": 4,
    "type": "ns",
    "value": 3.996647
  },
  {
    "matrix": 512,
    "block": 64,
    "cache": "16kB",
    "assoc": 8,
    "type": "ns",
    "value": 3.991851
  },
  {
    "matrix": 512,
    "block": 64,
    "cache": "32kB",
    "assoc": 4,
    "type": "ns",
    "value": 3.884793
  },
  {
    "matrix": 512,
    "block": 64,
    "cache": "32kB",
    "assoc": 8,
    "type": "ns",
    "value": 3.882143
  },
  {
    "matrix": 512,
    "block": 64,
    "cache": "64kB",
    "assoc": 4,
    "type": "ns",
    "value": 3.880069
  },
  {
    "matrix": 512,
    "block": 64,
    "cache": "64kB",
    "assoc": 8,
    "type": "ns",
    "value": 3.880054
  },
  {
    "matrix": 512,
    "block": 128,
    "cache": "16kB",
    "assoc": 4,
    "type": "ns",
    "value": 4.138745
  },
  {
    "matrix": 512,
    "block": 128,
    "cache": "16kB",
    "assoc": 8,
    "type": "ns",
    "value": 4.027448
  },
  {
    "matrix": 512,
    "block": 128,
    "cache": "32kB",
    "assoc": 4,
    "type": "ns",
    "value": 4.026504
  },
  {
    "matrix": 512,
    "block": 128,
    "cache": "32kB",
    "assoc": 8,
    "type": "ns",
    "value": 4.025865
  },
  {
    "matrix": 512,
    "block": 128,
    "cache": "64kB",
    "assoc": 4,
    "type": "ns",
    "value": 3.955513
  },
  {
    "matrix": 512,
    "block": 128,
    "cache": "64kB",
    "assoc": 8,
    "type": "ns",
    "value": 3.997055
  },
  {
    "matrix": 512,
    "block": 256,
    "cache": "16kB",
    "assoc": 4,
    "type": "ns",
    "value": 5.793164
  },
  {
    "matrix": 512,
    "block": 256,
    "cache": "16kB",
    "assoc": 8,
    "type": "ns",
    "value": 6.382196
  },
  {
    "matrix": 512,
    "block": 256,
    "cache": "32kB",
    "assoc": 4,
    "type": "ns",
    "value": 4.055996
  },
  {
    "matrix": 512,
    "block": 256,
    "cache": "32kB",
    "assoc": 8,
    "type": "ns",
    "value": 4.020293
  },
  {
    "matrix": 512,
    "block": 256,
    "cache": "64kB",
    "assoc": 4,
    "type": "ns",
    "value": 4.019807
  },
  {
    "matrix": 512,
    "block": 256,
    "cache": "64kB",
    "assoc": 8,
    "type": "ns",
    "value": 4.019807
  },
  {
    "matrix": 512,
    "block": 512,
    "cache": "16kB",
    "assoc": 4,
    "type": "ns",
    "value": 6.432232
  },
  {
    "matrix": 512,
    "block": 512,
    "cache": "16kB",
    "assoc": 8,
    "type": "ns",
    "value": 6.432232
  },
  {
    "matrix": 512,
    "block": 512,
    "cache": "32kB",
    "assoc": 4,
    "type": "ns",
    "value": 5.742615
  },
  {
    "matrix": 512,
    "block": 512,
    "cache": "32kB",
    "assoc": 8,
    "type": "ns",
    "value": 6.408165
  },
  {
    "matrix": 512,
    "block": 512,
    "cache": "64kB",
    "assoc": 4,
    "type": "ns",
    "value": 4.049752
  },
  {
    "matrix": 512,
    "block": 512,
    "cache": "64kB",
    "assoc": 8,
    "type": "ns",
    "value": 4.016633
  },
  {
    "matrix": 100,
    "block": 16,
    "cache": "16kB",
    "assoc": 4,
    "type": "ps",
    "value": 36.590482
  },
  {
    "matrix": 100,
    "block": 16,
    "cache": "16kB",
    "assoc": 8,
    "type": "ps",
    "value": 37.329785
  },
  {
    "matrix": 100,
    "block": 16,
    "cache": "32kB",
    "assoc": 4,
    "type": "ps",
    "value": 20.196755
  },
  {
    "matrix": 100,
    "block": 16,
    "cache": "32kB",
    "assoc": 8,
    "type": "ps",
    "value": 19.863435
  },
  {
    "matrix": 100,
    "block": 16,
    "cache": "64kB",
    "assoc": 4,
    "type": "ps",
    "value": 11.079842
  },
  {
    "matrix": 100,
    "block": 16,
    "cache": "64kB",
    "assoc": 8,
    "type": "ps",
    "value": 11.881002
  },
  {
    "matrix": 100,
    "block": 32,
    "cache": "16kB",
    "assoc": 4,
    "type": "ps",
    "value": 19.600474
  },
  {
    "matrix": 100,
    "block": 32,
    "cache": "16kB",
    "assoc": 8,
    "type": "ps",
    "value": 19.71355
  },
  {
    "matrix": 100,
    "block": 32,
    "cache": "32kB",
    "assoc": 4,
    "type": "ps",
    "value": 17.316916
  },
  {
    "matrix": 100,
    "block": 32,
    "cache": "32kB",
    "assoc": 8,
    "type": "ps",
    "value": 17.743402
  },
  {
    "matrix": 100,
    "block": 32,
    "cache": "64kB",
    "assoc": 4,
    "type": "ps",
    "value": 9.770088
  },
  {
    "matrix": 100,
    "block": 32,
    "cache": "64kB",
    "assoc": 8,
    "type": "ps",
    "value": 9.645462
  },
  {
    "matrix": 100,
    "block": 64,
    "cache": "16kB",
    "assoc": 4,
    "type": "ps",
    "value": 55.206039
  },
  {
    "matrix": 100,
    "block": 64,
    "cache": "16kB",
    "assoc": 8,
    "type": "ps",
    "value": 61.986151
  },
  {
    "matrix": 100,
    "block": 64,
    "cache": "32kB",
    "assoc": 4,
    "type": "ps",
    "value": 12.241903
  },
  {
    "matrix": 100,
    "block": 64,
    "cache": "32kB",
    "assoc": 8,
    "type": "ps",
    "value": 11.012821
  },
  {
    "matrix": 100,
    "block": 64,
    "cache": "64kB",
    "assoc": 4,
    "type": "ps",
    "value": 8.905523
  },
  {
    "matrix": 100,
    "block": 64,
    "cache": "64kB",
    "assoc": 8,
    "type": "ps",
    "value": 9.19285
  },
  {
    "matrix": 128,
    "block": 16,
    "cache": "16kB",
    "assoc": 4,
    "type": "ps",
    "value": 29.34581
  },
  {
    "matrix": 128,
    "block": 16,
    "cache": "16kB",
    "assoc": 8,
    "type": "ps",
    "value": 29.343283
  },
  {
    "matrix": 128,
    "block": 16,
    "cache": "32kB",
    "assoc": 4,
    "type": "ps",
    "value": 18.964489
  },
  {
    "matrix": 128,
    "block": 16,
    "cache": "32kB",
    "assoc": 8,
    "type": "ps",
    "value": 18.866538
  },
  {
    "matrix": 128,
    "block": 16,
    "cache": "64kB",
    "assoc": 4,
    "type": "ps",
    "value": 13.787203
  },
  {
    "matrix": 128,
    "block": 16,
    "cache": "64kB",
    "assoc": 8,
    "type": "ps",
    "value": 12.26645
  },
  {
    "matrix": 128,
    "block": 32,
    "cache": "16kB",
    "assoc": 4,
    "type": "ps",
    "value": 14.203493
  },
  {
    "matrix": 128,
    "block": 32,
    "cache": "16kB",
    "assoc": 8,
    "type": "ps",
    "value": 14.155479
  },
  {
    "matrix": 128,
    "block": 32,
    "cache": "32kB",
    "assoc": 4,
    "type": "ps",
    "value": 13.909396
  },
  {
    "matrix": 128,
    "block": 32,
    "cache": "32kB",
    "assoc": 8,
    "type": "ps",
    "value": 14.186148
  },
  {
    "matrix": 128,
    "block": 32,
    "cache": "64kB",
    "assoc": 4,
    "type": "ps",
    "value": 11.637185
  },
  {
    "matrix": 128,
    "block": 32,
    "cache": "64kB",
    "assoc": 8,
    "type": "ps",
    "value": 9.544896
  },
  {
    "matrix": 128,
    "block": 64,
    "cache": "16kB",
    "assoc": 4,
    "type": "ps",
    "value": 106.465481
  },
  {
    "matrix": 128,
    "block": 64,
    "cache": "16kB",
    "assoc": 8,
    "type": "ps",
    "value": 124.562529
  },
  {
    "matrix": 128,
    "block": 64,
    "cache": "32kB",
    "assoc": 4,
    "type": "ps",
    "value": 10.458135
  },
  {
    "matrix": 128,
    "block": 64,
    "cache": "32kB",
    "assoc": 8,
    "type": "ps",
    "value": 8.556175
  },
  {
    "matrix": 128,
    "block": 64,
    "cache": "64kB",
    "assoc": 4,
    "type": "ps",
    "value": 8.178746
  },
  {
    "matrix": 128,
    "block": 64,
    "cache": "64kB",
    "assoc": 8,
    "type": "ps",
    "value": 8.391094
  },
  {
    "matrix": 128,
    "block": 128,
    "cache": "16kB",
    "assoc": 4,
    "type": "ps",
    "value": 173.616803
  },
  {
    "matrix": 128,
    "block": 128,
    "cache": "16kB",
    "assoc": 8,
    "type": "ps",
    "value": 142.272905
  },
  {
    "matrix": 128,
    "block": 128,
    "cache": "32kB",
    "assoc": 4,
    "type": "ps",
    "value": 142.179318
  },
  {
    "matrix": 128,
    "block": 128,
    "cache": "32kB",
    "assoc": 8,
    "type": "ps",
    "value": 142.193834
  },
  {
    "matrix": 128,
    "block": 128,
    "cache": "64kB",
    "assoc": 4,
    "type": "ps",
    "value": 70.85799
  },
  {
    "matrix": 128,
    "block": 128,
    "cache": "64kB",
    "assoc": 8,
    "type": "ps",
    "value": 105.067649
  },
  {
    "matrix": 200,
    "block": 16,
    "cache": "16kB",
    "assoc": 4,
    "type": "ps",
    "value": 30.074001
  },
  {
    "matrix": 200,
    "block": 16,
    "cache": "16kB",
    "assoc": 8,
    "type": "ps",
    "value": 29.768666
  },
  {
    "matrix": 200,
    "block": 16,
    "cache": "32kB",
    "assoc": 4,
    "type": "ps",
    "value": 28.246459
  },
  {
    "matrix": 200,
    "block": 16,
    "cache": "32kB",
    "assoc": 8,
    "type": "ps",
    "value": 28.578045
  },
  {
    "matrix": 200,
    "block": 16,
    "cache": "64kB",
    "assoc": 4,
    "type": "ps",
    "value": 15.948091
  },
  {
    "matrix": 200,
    "block": 16,
    "cache": "64kB",
    "assoc": 8,
    "type": "ps",
    "value": 12.483467
  },
  {
    "matrix": 200,
    "block": 32,
    "cache": "16kB",
    "assoc": 4,
    "type": "ps",
    "value": 27.671338
  },
  {
    "matrix": 200,
    "block": 32,
    "cache": "16kB",
    "assoc": 8,
    "type": "ps",
    "value": 14.726454
  },
  {
    "matrix": 200,
    "block": 32,
    "cache": "32kB",
    "assoc": 4,
    "type": "ps",
    "value": 14.665058
  },
  {
    "matrix": 200,
    "block": 32,
    "cache": "32kB",
    "assoc": 8,
    "type": "ps",
    "value": 14.661764
  },
  {
    "matrix": 200,
    "block": 32,
    "cache": "64kB",
    "assoc": 4,
    "type": "ps",
    "value": 12.562142
  },
  {
    "matrix": 200,
    "block": 32,
    "cache": "64kB",
    "assoc": 8,
    "type": "ps",
    "value": 12.804348
  },
  {
    "matrix": 200,
    "block": 64,
    "cache": "16kB",
    "assoc": 4,
    "type": "ps",
    "value": 101.467186
  },
  {
    "matrix": 200,
    "block": 64,
    "cache": "16kB",
    "assoc": 8,
    "type": "ps",
    "value": 122.539732
  },
  {
    "matrix": 200,
    "block": 64,
    "cache": "32kB",
    "assoc": 4,
    "type": "ps",
    "value": 11.868698
  },
  {
    "matrix": 200,
    "block": 64,
    "cache": "32kB",
    "assoc": 8,
    "type": "ps",
    "value": 10.375352
  },
  {
    "matrix": 200,
    "block": 64,
    "cache": "64kB",
    "assoc": 4,
    "type": "ps",
    "value": 8.863376
  },
  {
    "matrix": 200,
    "block": 64,
    "cache": "64kB",
    "assoc": 8,
    "type": "ps",
    "value": 8.879165
  },
  {
    "matrix": 200,
    "block": 128,
    "cache": "16kB",
    "assoc": 4,
    "type": "ps",
    "value": 201.172789
  },
  {
    "matrix": 200,
    "block": 128,
    "cache": "16kB",
    "assoc": 8,
    "type": "ps",
    "value": 154.500774
  },
  {
    "matrix": 200,
    "block": 128,
    "cache": "32kB",
    "assoc": 4,
    "type": "ps",
    "value": 124.158638
  },
  {
    "matrix": 200,
    "block": 128,
    "cache": "32kB",
    "assoc": 8,
    "type": "ps",
    "value": 131.260163
  },
  {
    "matrix": 200,
    "block": 128,
    "cache": "64kB",
    "assoc": 4,
    "type": "ps",
    "value": 40.13835
  },
  {
    "matrix": 200,
    "block": 128,
    "cache": "64kB",
    "assoc": 8,
    "type": "ps",
    "value": 47.685647
  },
  {
    "matrix": 256,
    "block": 16,
    "cache": "16kB",
    "assoc": 4,
    "type": "ps",
    "value": 28.367444
  },
  {
    "matrix": 256,
    "block": 16,
    "cache": "16kB",
    "assoc": 8,
    "type": "ps",
    "value": 28.263359
  },
  {
    "matrix": 256,
    "block": 16,
    "cache": "32kB",
    "assoc": 4,
    "type": "ps",
    "value": 26.588761
  },
  {
    "matrix": 256,
    "block": 16,
    "cache": "32kB",
    "assoc": 8,
    "type": "ps",
    "value": 28.40383
  },
  {
    "matrix": 256,
    "block": 16,
    "cache": "64kB",
    "assoc": 4,
    "type": "ps",
    "value": 22.955014
  },
  {
    "matrix": 256,
    "block": 16,
    "cache": "64kB",
    "assoc": 8,
    "type": "ps",
    "value": 20.47527
  },
  {
    "matrix": 256,
    "block": 32,
    "cache": "16kB",
    "assoc": 4,
    "type": "ps",
    "value": 13.926645
  },
  {
    "matrix": 256,
    "block": 32,
    "cache": "16kB",
    "assoc": 8,
    "type": "ps",
    "value": 12.830338
  },
  {
    "matrix": 256,
    "block": 32,
    "cache": "32kB",
    "assoc": 4,
    "type": "ps",
    "value": 12.760332
  },
  {
    "matrix": 256,
    "block": 32,
    "cache": "32kB",
    "assoc": 8,
    "type": "ps",
    "value": 12.834882
  },
  {
    "matrix": 256,
    "block": 32,
    "cache": "64kB",
    "assoc": 4,
    "type": "ps",
    "value": 11.949793
  },
  {
    "matrix": 256,
    "block": 32,
    "cache": "64kB",
    "assoc": 8,
    "type": "ps",
    "value": 12.180274
  },
  {
    "matrix": 256,
    "block": 64,
    "cache": "16kB",
    "assoc": 4,
    "type": "ps",
    "value": 163.024364
  },
  {
    "matrix": 256,
    "block": 64,
    "cache": "16kB",
    "assoc": 8,
    "type": "ps",
    "value": 150.502088
  },
  {
    "matrix": 256,
    "block": 64,
    "cache": "32kB",
    "assoc": 4,
    "type": "ps",
    "value": 21.739295
  },
  {
    "matrix": 256,
    "block": 64,
    "cache": "32kB",
    "assoc": 8,
    "type": "ps",
    "value": 7.9492
  },
  {
    "matrix": 256,
    "block": 64,
    "cache": "64kB",
    "assoc": 4,
    "type": "ps",
    "value": 9.782859
  },
  {
    "matrix": 256,
    "block": 64,
    "cache": "64kB",
    "assoc": 8,
    "type": "ps",
    "value": 7.228004
  },
  {
    "matrix": 256,
    "block": 128,
    "cache": "16kB",
    "assoc": 4,
    "type": "ps",
    "value": 644.616837
  },
  {
    "matrix": 256,
    "block": 128,
    "cache": "16kB",
    "assoc": 8,
    "type": "ps",
    "value": 162.007017
  },
  {
    "matrix": 256,
    "block": 128,
    "cache": "32kB",
    "assoc": 4,
    "type": "ps",
    "value": 408.678258
  },
  {
    "matrix": 256,
    "block": 128,
    "cache": "32kB",
    "assoc": 8,
    "type": "ps",
    "value": 161.028246
  },
  {
    "matrix": 256,
    "block": 128,
    "cache": "64kB",
    "assoc": 4,
    "type": "ps",
    "value": 266.171812
  },
  {
    "matrix": 256,
    "block": 128,
    "cache": "64kB",
    "assoc": 8,
    "type": "ps",
    "value": 100.536554
  },
  {
    "matrix": 256,
    "block": 256,
    "cache": "16kB",
    "assoc": 4,
    "type": "ps",
    "value": 1578.52066
  },
  {
    "matrix": 256,
    "block": 256,
    "cache": "16kB",
    "assoc": 8,
    "type": "ps",
    "value": 2166.439505
  },
  {
    "matrix": 256,
    "block": 256,
    "cache": "32kB",
    "assoc": 4,
    "type": "ps",
    "value": 787.004271
  },
  {
    "matrix": 256,
    "block": 256,
    "cache": "32kB",
    "assoc": 8,
    "type": "ps",
    "value": 156.913668
  },
  {
    "matrix": 256,
    "block": 256,
    "cache": "64kB",
    "assoc": 4,
    "type": "ps",
    "value": 472.862737
  },
  {
    "matrix": 256,
    "block": 256,
    "cache": "64kB",
    "assoc": 8,
    "type": "ps",
    "value": 156.913112
  },
  {
    "matrix": 512,
    "block": 16,
    "cache": "16kB",
    "assoc": 4,
    "type": "ps",
    "value": 29.195741
  },
  {
    "matrix": 512,
    "block": 16,
    "cache": "16kB",
    "assoc": 8,
    "type": "ps",
    "value": 28.904184
  },
  {
    "matrix": 512,
    "block": 16,
    "cache": "32kB",
    "assoc": 4,
    "type": "ps",
    "value": 28.879856
  },
  {
    "matrix": 512,
    "block": 16,
    "cache": "32kB",
    "assoc": 8,
    "type": "ps",
    "value": 28.859709
  },
  {
    "matrix": 512,
    "block": 16,
    "cache": "64kB",
    "assoc": 4,
    "type": "ps",
    "value": 28.87339
  },
  {
    "matrix": 512,
    "block": 16,
    "cache": "64kB",
    "assoc": 8,
    "type": "ps",
    "value": 28.858159
  },
  {
    "matrix": 512,
    "block": 32,
    "cache": "16kB",
    "assoc": 4,
    "type": "ps",
    "value": 13.347342
  },
  {
    "matrix": 512,
    "block": 32,
    "cache": "16kB",
    "assoc": 8,
    "type": "ps",
    "value": 12.634625
  },
  {
    "matrix": 512,
    "block": 32,
    "cache": "32kB",
    "assoc": 4,
    "type": "ps",
    "value": 12.571692
  },
  {
    "matrix": 512,
    "block": 32,
    "cache": "32kB",
    "assoc": 8,
    "type": "ps",
    "value": 12.581084
  },
  {
    "matrix": 512,
    "block": 32,
    "cache": "64kB",
    "assoc": 4,
    "type": "ps",
    "value": 12.597231
  },
  {
    "matrix": 512,
    "block": 32,
    "cache": "64kB",
    "assoc": 8,
    "type": "ps",
    "value": 12.570096
  },
  {
    "matrix": 512,
    "block": 64,
    "cache": "16kB",
    "assoc": 4,
    "type": "ps",
    "value": 127.720887
  },
  {
    "matrix": 512,
    "block": 64,
    "cache": "16kB",
    "assoc": 8,
    "type": "ps",
    "value": 122.71782
  },
  {
    "matrix": 512,
    "block": 64,
    "cache": "32kB",
    "assoc": 4,
    "type": "ps",
    "value": 11.088528
  },
  {
    "matrix": 512,
    "block": 64,
    "cache": "32kB",
    "assoc": 8,
    "type": "ps",
    "value": 8.697942
  },
  {
    "matrix": 512,
    "block": 64,
    "cache": "64kB",
    "assoc": 4,
    "type": "ps",
    "value": 6.669677
  },
  {
    "matrix": 512,
    "block": 64,
    "cache": "64kB",
    "assoc": 8,
    "type": "ps",
    "value": 6.650916
  },
  {
    "matrix": 512,
    "block": 128,
    "cache": "16kB",
    "assoc": 4,
    "type": "ps",
    "value": 275.737901
  },
  {
    "matrix": 512,
    "block": 128,
    "cache": "16kB",
    "assoc": 8,
    "type": "ps",
    "value": 166.504065
  },
  {
    "matrix": 512,
    "block": 128,
    "cache": "32kB",
    "assoc": 4,
    "type": "ps",
    "value": 165.702661
  },
  {
    "matrix": 512,
    "block": 128,
    "cache": "32kB",
    "assoc": 8,
    "type": "ps",
    "value": 164.995314
  },
  {
    "matrix": 512,
    "block": 128,
    "cache": "64kB",
    "assoc": 4,
    "type": "ps",
    "value": 86.341652
  },
  {
    "matrix": 512,
    "block": 128,
    "cache": "64kB",
    "assoc": 8,
    "type": "ps",
    "value": 133.051521
  },
  {
    "matrix": 512,
    "block": 256,
    "cache": "16kB",
    "assoc": 4,
    "type": "ps",
    "value": 1958.340899
  },
  {
    "matrix": 512,
    "block": 256,
    "cache": "16kB",
    "assoc": 8,
    "type": "ps",
    "value": 2532.285145
  },
  {
    "matrix": 512,
    "block": 256,
    "cache": "32kB",
    "assoc": 4,
    "type": "ps",
    "value": 199.400331
  },
  {
    "matrix": 512,
    "block": 256,
    "cache": "32kB",
    "assoc": 8,
    "type": "ps",
    "value": 158.598924
  },
  {
    "matrix": 512,
    "block": 256,
    "cache": "64kB",
    "assoc": 4,
    "type": "ps",
    "value": 158.114324
  },
  {
    "matrix": 512,
    "block": 256,
    "cache": "64kB",
    "assoc": 8,
    "type": "ps",
    "value": 158.117177
  },
  {
    "matrix": 512,
    "block": 512,
    "cache": "16kB",
    "assoc": 4,
    "type": "ps",
    "value": 2578.903201
  },
  {
    "matrix": 512,
    "block": 512,
    "cache": "16kB",
    "assoc": 8,
    "type": "ps",
    "value": 2578.904962
  },
  {
    "matrix": 512,
    "block": 512,
    "cache": "32kB",
    "assoc": 4,
    "type": "ps",
    "value": 1823.873604
  },
  {
    "matrix": 512,
    "block": 512,
    "cache": "32kB",
    "assoc": 8,
    "type": "ps",
    "value": 2563.84155
  },
  {
    "matrix": 512,
    "block": 512,
    "cache": "64kB",
    "assoc": 4,
    "type": "ps",
    "value": 185.390379
  },
  {
    "matrix": 512,
    "block": 512,
    "cache": "64kB",
    "assoc": 8,
    "type": "ps",
    "value": 155.008252
  }
]